nv_one_logger/no_init.md
nv_one_logger/otel/exporter/__init__.py
nv_one_logger/otel/exporter/otel_exporter.py
nv_one_logger/otel/no_init.md
nv_one_logger_otel-2.3.0.dist-info/LICENSE
nv_one_logger_otel-2.3.0.dist-info/METADATA
nv_one_logger_otel-2.3.0.dist-info/WHEEL
nv_one_logger_otel-2.3.0.dist-info/RECORD
